{
  "libraries": [
    {
      "name": "LAFAYETTE PUBLIC LIBRARY",
      "system": "LAFAYETTE PUBLIC LIBRARY",
      "address": "301 W CONGRESS ST, LAFAYETTE, LA",
      "website": "https://lafayetteco.gov/2570/Library",
      "formUrl": null,
      "formStatus": "unknown",
      "zipcodes": [
        "13063",
        "13084",
        "13110",
        "13120",
        "70501",
        "70503",
        "70506",
        "70507",
        "70508",
        "70518",
        "70520",
        "70529",
        "70558",
        "70583",
        "70592",
        "80026",
        "80301",
        "80303",
        "80516"
      ]
    },
    {
      "name": "LANSING COMMUNITY LIBRARY",
      "system": "LANSING COMMUNITY LIBRARY",
      "address": "730 1ST TERRACE, LANSING, KS",
      "website": "https://lansing.nextkansas.org/",
      "formUrl": null,
      "formStatus": "unknown",
      "zipcodes": [
        "13062",
        "13068",
        "13073",
        "14882",
        "66027",
        "66043"
      ]
    },
    {
      "name": "MORRISVILLE PUBLIC LIBRARY",
      "system": "MORRISVILLE PUBLIC LIBRARY",
      "address": "83 EAST MAIN STREET, MORRISVILLE, NY",
      "website": "https://morrisvillepubliclibrary.org/",
      "formUrl": "https://morrisvillepubliclibrary.org/suggested-book-lists/",
      "formStatus": "verified",
      "zipcodes": [
        "13061",
        "13310",
        "13334",
        "13346",
        "13402",
        "13408",
        "13409"
      ]
    },
    {
      "name": "SHERRILL-KENWOOD FREE LIBRARY",
      "system": "SHERRILL-KENWOOD FREE LIBRARY",
      "address": "543 SHERRILL ROAD, SHERRILL, NY",
      "website": "https://sherrillkenwoodlibrary.org/",
      "formUrl": null,
      "formStatus": "unknown",
      "zipcodes": [
        "13054",
        "13461",
        "13477",
        "13478"
      ]
    },
    {
      "name": "VERNON PUBLIC LIBRARY",
      "system": "VERNON PUBLIC LIBRARY",
      "address": "4441 PETERBORO STREET, VERNON, NY",
      "website": "https://vernonpubliclibrary.org/",
      "formUrl": null,
      "formStatus": "unknown",
      "zipcodes": [
        "13054",
        "13476",
        "13477",
        "13478",
        "13490"
      ]
    },
    {
      "name": "COGSWELL FREE LIBRARY",
      "system": "COGSWELL FREE LIBRARY",
      "address": "1999 COUNTY ROUTE 2, ORWELL, NY",
      "website": "https://cogswellfreelibrary.org/",
      "formUrl": null,
      "formStatus": "unknown",
      "zipcodes": [
        "13083",
        "13144",
        "13302",
        "13426",
        "13437"
      ]
    },
    {
      "name": "WILLIAMSTOWN LIBRARY",
      "system": "WILLIAMSTOWN LIBRARY",
      "address": "2877 COUNTY ROUTE 17N, WILLIAMSTOWN, NY",
      "website": "https://williamstownlibrary.org/locations/",
      "formUrl": null,
      "formStatus": "unknown",
      "zipcodes": [
        "13028",
        "13302",
        "13493"
      ]
    },
    {
      "name": "CAMDEN LIBRARY ASSOCIATION",
      "system": "CAMDEN LIBRARY ASSOCIATION",
      "address": "57 SECOND STREET, CAMDEN, NY",
      "website": "https://camden.midyork.org/",
      "formUrl": null,
      "formStatus": "unknown",
      "zipcodes": [
        "13042",
        "13308",
        "13316",
        "13471",
        "13483"
      ]
    },
    {
      "name": "TOMPKINS COUNTY PUBLIC LIBRARY",
      "system": "TOMPKINS COUNTY PUBLIC LIBRARY",
      "address": "101 EAST GREEN STREET, ITHACA, NY",
      "website": "http://www.tcpl.org",
      "formUrl": "https://www.tcpl.org/form/suggest-a-title",
      "formStatus": "verified",
      "zipcodes": [
        "13062",
        "14850",
        "14881"
      ]
    },
    {
      "name": "SALINA FREE LIBRARY",
      "system": "SALINA FREE LIBRARY",
      "address": "100 BELMONT ST., MATTYDALE, NY",
      "website": "https://salinalibrary.org/",
      "formUrl": null,
      "formStatus": "unknown",
      "zipcodes": [
        "13029",
        "13041",
        "13090",
        "13203",
        "13206",
        "13208",
        "13211",
        "13212",
        "13290"
      ]
    },
    {
      "name": "ONONDAGA FREE LIBRARY",
      "system": "ONONDAGA FREE LIBRARY",
      "address": "4840 WEST SENECA TURNPIKE, SYRACUSE, NY",
      "website": "https://oflibrary.org/",
      "formUrl": "https://oflibrary.org/check-it-out/request-an-interlibrary-loan/",
      "formStatus": "verified",
      "zipcodes": [
        "13084",
        "13120",
        "13204",
        "13205",
        "13207",
        "13210",
        "13215"
      ]
    },
    {
      "name": "POWERS LIBRARY ASSOCIATION",
      "system": "POWERS LIBRARY ASSOCIATION",
      "address": "29 CHURCH STREET, MORAVIA, NY",
      "website": "https://powerslibraryny.org/",
      "formUrl": null,
      "formStatus": "unknown",
      "zipcodes": [
        "13071",
        "13092",
        "13118"
      ]
    },
    {
      "name": "HAZARD LIBRARY ASSOCIATION",
      "system": "HAZARD LIBRARY ASSOCIATION",
      "address": "2487 ROUTE 34B, POPLAR RIDGE, NY",
      "website": "https://catalog.flls.org/polaris/library/hours.aspx?ctx=51.1033.0.0.3",
      "formUrl": "https://catalog.flls.org/polaris/library/hours.aspx?ctx=51.1033.0.0.3/javascript:showModalBasicWithIframe(%27https://catalog.flls.org/polaris/help/content/1033/request.htm%27)",
      "formStatus": "verified",
      "zipcodes": [
        "13071",
        "13081",
        "13139",
        "13147"
      ]
    },
    {
      "name": "SPRINGPORT FREE LIBRARY",
      "system": "SPRINGPORT FREE LIBRARY",
      "address": "171 CAYUGA STREET, UNION SPRINGS, NY",
      "website": "https://springportfreelibrary.org/",
      "formUrl": null,
      "formStatus": "unknown",
      "zipcodes": [
        "13034",
        "13147",
        "13160"
      ]
    },
    {
      "name": "NEW WOODSTOCK FREE LIBRARY",
      "system": "NEW WOODSTOCK FREE LIBRARY",
      "address": "2106 MAIN STREET, NEW WOODSTOCK, NY",
      "website": "https://newwoodstocklibrary.org/",
      "formUrl": null,
      "formStatus": "unknown",
      "zipcodes": [
        "13061",
        "13072",
        "13122"
      ]
    },
    {
      "name": "MEXICO PUBLIC LIBRARY",
      "system": "MEXICO PUBLIC LIBRARY",
      "address": "3269 MAIN STREET, MEXICO, NY",
      "website": "https://mexicopubliclibrary.org/",
      "formUrl": "https://mexicopubliclibrary.org/interlibrary-loan/",
      "formStatus": "verified",
      "zipcodes": [
        "13076",
        "13114"
      ]
    },
    {
      "name": "PARISH PUBLIC LIBRARY",
      "system": "PARISH PUBLIC LIBRARY",
      "address": "3 CHURCH STREET, PARISH, NY",
      "website": "https://parishpubliclibrary.org/",
      "formUrl": "https://parishpubliclibrary.org/interlibrary-loan/",
      "formStatus": "verified",
      "zipcodes": [
        "13076",
        "13131",
        "13167"
      ]
    },
    {
      "name": "PULASKI PUBLIC LIBRARY",
      "system": "PULASKI PUBLIC LIBRARY",
      "address": "4917 NORTH JEFFERSON STREET, PULASKI, NY",
      "website": "https://pulaskinypubliclibrary.org/",
      "formUrl": null,
      "formStatus": "unknown",
      "zipcodes": [
        "13083",
        "13142",
        "13144",
        "13302"
      ]
    },
    {
      "name": "ANNIE PORTER AINSWORTH MEMORIAL LIBRARY",
      "system": "ANNIE PORTER AINSWORTH MEMORIAL LIBRARY",
      "address": "6064 SOUTH MAIN STREET, SANDY CREEK, NY",
      "website": "https://ainsworthmemoriallibrary.org/",
      "formUrl": "https://ainsworthmemoriallibrary.org/how-to-place-a-hold-from-home/",
      "formStatus": "verified",
      "zipcodes": [
        "13083",
        "13144",
        "13145"
      ]
    },
    {
      "name": "MINOA LIBRARY",
      "system": "MINOA LIBRARY",
      "address": "242 N. MAIN STREET, MINOA, NY",
      "website": "http://www.minoalibrary.org/",
      "formUrl": null,
      "formStatus": "unknown",
      "zipcodes": [
        "13030",
        "13116"
      ]
    },
    {
      "name": "TULLY FREE LIBRARY",
      "system": "TULLY FREE LIBRARY",
      "address": "12 STATE STREET, TULLY, NY",
      "website": "https://www.tullyfreelibrary.org/",
      "formUrl": "https://www.tullyfreelibrary.org/suggest-a-purchase",
      "formStatus": "verified",
      "zipcodes": [
        "13063",
        "13084",
        "13159"
      ]
    },
    {
      "name": "PORT BYRON LIBRARY",
      "system": "PORT BYRON LIBRARY",
      "address": "12 SPONABLE DRIVE, PORT BYRON, NY",
      "website": "https://portbyronlibrary.org/",
      "formUrl": null,
      "formStatus": "unknown",
      "zipcodes": [
        "13034",
        "13140"
      ]
    },
    {
      "name": "GROTON PUBLIC LIBRARY",
      "system": "GROTON PUBLIC LIBRARY",
      "address": "99 MAIN STREET, GROTON, MA",
      "website": "https://www.groton-ct.gov/departments/library/index.php",
      "formUrl": "https://www.groton-ct.gov/dept_news_detail_T23_R945.php",
      "formStatus": "verified",
      "zipcodes": [
        "01450",
        "13068",
        "13073",
        "14882"
      ]
    },
    {
      "name": "THE SOUTHWORTH LIBRARY ASSOCIATION",
      "system": "THE SOUTHWORTH LIBRARY ASSOCIATION",
      "address": "24 WEST MAIN STREET, DRYDEN, NY",
      "website": "https://southworthlibrary.org/",
      "formUrl": null,
      "formStatus": "unknown",
      "zipcodes": [
        "13053",
        "13062",
        "13068",
        "13073",
        "14817",
        "14881"
      ]
    },
    {
      "name": "SEYMOUR PUBLIC LIBRARY DISTRICT",
      "system": "SEYMOUR PUBLIC LIBRARY DISTRICT",
      "address": "176-178 GENESEE STREET, AUBURN, NY",
      "website": "http://www.seymourlibrary.org/",
      "formUrl": null,
      "formStatus": "unknown",
      "zipcodes": [
        "13021",
        "13034"
      ]
    },
    {
      "name": "AURORA FREE LIBRARY",
      "system": "AURORA FREE LIBRARY",
      "address": "370 MAIN STREET, AURORA, NY",
      "website": "https://aurorafreelibrary.org/",
      "formUrl": null,
      "formStatus": "unknown",
      "zipcodes": [
        "13026",
        "13071",
        "13081",
        "13147"
      ]
    },
    {
      "name": "STEWART B. LANG MEMORIAL LIBRARY",
      "system": "STEWART B. LANG MEMORIAL LIBRARY",
      "address": "2577 EAST MAIN STREET, CATO, NY",
      "website": "http://langlibrary.org/",
      "formUrl": null,
      "formStatus": "unknown",
      "zipcodes": [
        "13033",
        "13111"
      ]
    },
    {
      "name": "VILLAGE OF FAIR HAVEN PUBLIC LIBRARY",
      "system": "VILLAGE OF FAIR HAVEN PUBLIC LIBRARY",
      "address": "14426 SOUTH RICHMOND AVENUE, FAIR HAVEN, NY",
      "website": "https://fairhavenlibrary.org/services/",
      "formUrl": null,
      "formStatus": "unknown",
      "zipcodes": [
        "13064",
        "13111",
        "13156"
      ]
    },
    {
      "name": "KELLOGG FREE LIBRARY",
      "system": "KELLOGG FREE LIBRARY",
      "address": "5681 TELEPHONE ROAD EXTENSION, CINCINNATUS, NY",
      "website": "https://kelloggfreelibrary.org/",
      "formUrl": null,
      "formStatus": "unknown",
      "zipcodes": [
        "13040",
        "13863"
      ]
    },
    {
      "name": "CORTLAND FREE LIBRARY",
      "system": "CORTLAND FREE LIBRARY",
      "address": "32 CHURCH STREET, CORTLAND, NY",
      "website": "http://cortlandfreelibrary.org/",
      "formUrl": null,
      "formStatus": "unknown",
      "zipcodes": [
        "13045"
      ]
    },
    {
      "name": "PHILLIPS FREE LIBRARY",
      "system": "PHILLIPS FREE LIBRARY",
      "address": "37 SOUTH MAIN STREET, HOMER, NY",
      "website": "https://phillipsfreelibrary.org/",
      "formUrl": null,
      "formStatus": "unknown",
      "zipcodes": [
        "13077",
        "13141"
      ]
    },
    {
      "name": "CANASTOTA PUBLIC LIBRARY",
      "system": "CANASTOTA PUBLIC LIBRARY",
      "address": "102 WEST CENTER STREET, CANASTOTA, NY",
      "website": "https://www.canastotalibrary.org/",
      "formUrl": null,
      "formStatus": "unknown",
      "zipcodes": [
        "13032"
      ]
    },
    {
      "name": "CAZENOVIA PUBLIC LIBRARY SOCIETY",
      "system": "CAZENOVIA PUBLIC LIBRARY SOCIETY",
      "address": "100 ALBANY STREET, CAZENOVIA, NY",
      "website": "https://cazenoviapubliclibrary.org/",
      "formUrl": null,
      "formStatus": "unknown",
      "zipcodes": [
        "13035",
        "13061"
      ]
    },
    {
      "name": "SULLIVAN FREE LIBRARY",
      "system": "SULLIVAN FREE LIBRARY",
      "address": "101 FALLS BOULEVARD, CHITTENANGO, NY",
      "website": "https://sullivanfreelibrary.org/",
      "formUrl": null,
      "formStatus": "unknown",
      "zipcodes": [
        "13037",
        "13082"
      ]
    },
    {
      "name": "DERUYTER FREE LIBRARY",
      "system": "DERUYTER FREE LIBRARY",
      "address": "735 UTICA STREET, DERUYTER, NY",
      "website": "https://deruyterlibrary.org/",
      "formUrl": null,
      "formStatus": "unknown",
      "zipcodes": [
        "13052",
        "13072"
      ]
    },
    {
      "name": "CENTRAL SQUARE LIBRARY",
      "system": "CENTRAL SQUARE LIBRARY",
      "address": "637 SOUTH MAIN STREET, CENTRAL SQUARE, NY",
      "website": "https://centralsquarelibrary.org/",
      "formUrl": "https://centralsquarelibrary.org/services/interlibrary-loan/",
      "formStatus": "verified",
      "zipcodes": [
        "13036",
        "13044",
        "13076",
        "13132",
        "13135",
        "13167"
      ]
    },
    {
      "name": "FULTON PUBLIC LIBRARY",
      "system": "FULTON PUBLIC LIBRARY",
      "address": "160 SOUTH FIRST STREET, FULTON, NY",
      "website": "https://fultonpubliclibrary.org/",
      "formUrl": null,
      "formStatus": "unknown",
      "zipcodes": [
        "13069",
        "13132",
        "13135"
      ]
    },
    {
      "name": "HANNIBAL FREE LIBRARY",
      "system": "HANNIBAL FREE LIBRARY",
      "address": "162 OSWEGO STREET, HANNIBAL, NY",
      "website": "https://hannibalfreelibrary.org/",
      "formUrl": null,
      "formStatus": "unknown",
      "zipcodes": [
        "13074"
      ]
    },
    {
      "name": "BALDWINSVILLE PUBLIC LIBRARY",
      "system": "BALDWINSVILLE PUBLIC LIBRARY",
      "address": "33 EAST GENESEE STREET, BALDWINSVILLE, NY",
      "website": "https://www.bville.lib.ny.us/",
      "formUrl": null,
      "formStatus": "unknown",
      "zipcodes": [
        "13027",
        "13112",
        "13164"
      ]
    },
    {
      "name": "MAXWELL MEMORIAL LIBRARY",
      "system": "MAXWELL MEMORIAL LIBRARY",
      "address": "14 GENESEE STREET, CAMILLUS, NY",
      "website": "https://www.onlib.org/locations/suburban-libraries/maxwell-memorial-library",
      "formUrl": "https://www.onlib.org/locations/suburban-libraries/maxwell-memorial-library/find/ask/suggest-title-collection",
      "formStatus": "verified",
      "zipcodes": [
        "13031",
        "13164"
      ]
    },
    {
      "name": "COMMUNITY LIBRARY OF DEWITT & JAMESVILLE",
      "system": "COMMUNITY LIBRARY OF DEWITT & JAMESVILLE",
      "address": "5110 JAMESVILLE ROAD, JAMESVILLE, NY",
      "website": "https://www.cldandj.org/",
      "formUrl": null,
      "formStatus": "unknown",
      "zipcodes": [
        "13078",
        "13205",
        "13210",
        "13214",
        "13224"
      ]
    },
    {
      "name": "EAST SYRACUSE FREE LIBRARY",
      "system": "EAST SYRACUSE FREE LIBRARY",
      "address": "4990 JAMES STREET, EAST SYRACUSE, NY",
      "website": "https://www.eastsyracusefreelibrary.org/",
      "formUrl": null,
      "formStatus": "unknown",
      "zipcodes": [
        "13030",
        "13057",
        "13203",
        "13206",
        "13214",
        "13224"
      ]
    },
    {
      "name": "ELBRIDGE FREE LIBRARY",
      "system": "ELBRIDGE FREE LIBRARY",
      "address": "241 EAST MAIN STREET, ELBRIDGE, NY",
      "website": "https://elbridgelibrary.org/contact-us",
      "formUrl": null,
      "formStatus": "unknown",
      "zipcodes": [
        "13060",
        "13112"
      ]
    },
    {
      "name": "FAYETTEVILLE FREE LIBRARY",
      "system": "FAYETTEVILLE FREE LIBRARY",
      "address": "300 ORCHARD STREET, FAYETTEVILLE, NY",
      "website": "https://fflib.org/",
      "formUrl": null,
      "formStatus": "unknown",
      "zipcodes": [
        "13066",
        "13214"
      ]
    },
    {
      "name": "JORDAN BRAMLEY LIBRARY",
      "system": "JORDAN BRAMLEY LIBRARY",
      "address": "15 MECHANIC STREET, JORDAN, NY",
      "website": "https://jordanbramleylibrary.org/",
      "formUrl": null,
      "formStatus": "unknown",
      "zipcodes": [
        "13080",
        "13112"
      ]
    },
    {
      "name": "LIVERPOOL PUBLIC LIBRARY",
      "system": "LIVERPOOL PUBLIC LIBRARY",
      "address": "310 TULIP STREET, LIVERPOOL, NY",
      "website": "https://lpl.org/",
      "formUrl": "https://lpl.org/explore/my-account/suggest-a-purchase/",
      "formStatus": "verified",
      "zipcodes": [
        "13029",
        "13041",
        "13088",
        "13090",
        "13212"
      ]
    },
    {
      "name": "NORTHERN ONONDAGA PUBLIC LIBRARY",
      "system": "NORTHERN ONONDAGA PUBLIC LIBRARY",
      "address": "8686 KNOWLEDGE LANE, CICERO, NY",
      "website": "https://www.nopl.org/about-nopl/hours-and-locations/cicero/",
      "formUrl": null,
      "formStatus": "unknown",
      "zipcodes": [
        "13029",
        "13030",
        "13039",
        "13041",
        "13090",
        "13212"
      ]
    }
  ]
}