{
  "libraries": [
    {
      "name": "WESTMINSTER PUBLIC LIBRARY",
      "system": "WESTMINSTER PUBLIC LIBRARY",
      "address": "3705 W. 112TH AVE, WESTMINSTER, CO",
      "website": "https://www.westminsterco.gov/166/Libraries",
      "formUrl": null,
      "formStatus": "unknown",
      "zipcodes": [
        "80010",
        "80019",
        "80022",
        "80024",
        "80030",
        "80031",
        "800XX",
        "80102",
        "80136",
        "80137",
        "80221",
        "80229",
        "80233",
        "80234",
        "80241",
        "80260",
        "80601",
        "80640",
        "806HH"
      ]
    },
    {
      "name": "RANGEVIEW LIBRARY DISTRICT",
      "system": "RANGEVIEW LIBRARY DISTRICT",
      "address": "5877 EAST 120TH AVENUE, THORNTON, CO",
      "website": "https://www.anythinklibraries.org/",
      "formUrl": null,
      "formStatus": "unknown",
      "zipcodes": [
        "80010",
        "80019",
        "80022",
        "80024",
        "80030",
        "800XX",
        "80102",
        "80136",
        "80137",
        "80221",
        "80229",
        "80233",
        "80234",
        "80241",
        "80260",
        "80601",
        "80602",
        "80640",
        "806HH"
      ]
    },
    {
      "name": "HIGH PLAINS LIBRARY DISTRICT",
      "system": "HIGH PLAINS LIBRARY DISTRICT",
      "address": "2650 W. 29TH ST., GREELEY, CO",
      "website": "https://www.mylibrary.us/",
      "formUrl": null,
      "formStatus": "unknown",
      "zipcodes": [
        "80504",
        "80514",
        "80520",
        "80530",
        "80534",
        "80542",
        "80543",
        "80610",
        "80611",
        "80612",
        "80615",
        "80620",
        "80621",
        "80623",
        "80624",
        "80631",
        "80634",
        "80642",
        "80643",
        "80644",
        "80645",
        "80648",
        "80650",
        "80651",
        "80652",
        "80729",
        "80742",
        "80754"
      ]
    },
    {
      "name": "EAST MORGAN COUNTY LIBRARY DISTRICT/BRUSH",
      "system": "EAST MORGAN COUNTY LIBRARY DISTRICT/BRUSH",
      "address": "500 CLAYTON STREET, BRUSH, CO",
      "website": "https://emcld.org/",
      "formUrl": null,
      "formStatus": "unknown",
      "zipcodes": [
        "80649",
        "80653",
        "80654",
        "80705",
        "80723",
        "80733",
        "80750"
      ]
    },
    {
      "name": "FORT MORGAN PUBLIC LIBRARY",
      "system": "FORT MORGAN PUBLIC LIBRARY",
      "address": "414 MAIN STREET, FORT MORGAN, CO",
      "website": "https://cityoffortmorgan.com/99/Library",
      "formUrl": null,
      "formStatus": "unknown",
      "zipcodes": [
        "80649",
        "80653",
        "80654",
        "80701",
        "80705",
        "80733",
        "80750"
      ]
    },
    {
      "name": "CLEARVIEW LIBRARY DISTRICT",
      "system": "CLEARVIEW LIBRARY DISTRICT",
      "address": "720 THIRD STREET, WINDSOR, CO",
      "website": "https://clearviewlibrary.org/",
      "formUrl": null,
      "formStatus": "unknown",
      "zipcodes": [
        "80504",
        "80514",
        "80520",
        "80530",
        "80534",
        "80542",
        "80543",
        "80550",
        "80610",
        "80611",
        "80612",
        "80615",
        "80620",
        "80621",
        "80623",
        "80624",
        "80634",
        "80642",
        "80643",
        "80644",
        "80645",
        "80648",
        "80650",
        "80651",
        "80652",
        "80729",
        "80742",
        "80754"
      ]
    }
  ]
}