{
  "libraries": [
    {
      "name": "WELLS PUBLIC LIBRARY",
      "system": "WELLS PUBLIC LIBRARY",
      "address": "1434 POST ROAD, WELLS, ME",
      "website": "https://www.myacpl.org/wells/",
      "formUrl": "https://search.myacpl.org/MaterialsRequest/NewRequest",
      "formStatus": "verified",
      "zipcodes": [
        "03902",
        "04090",
        "56014",
        "56025",
        "56051",
        "56068",
        "56097"
      ],
      "id": "wells-public-library-me"
    },
    {
      "name": "WILLIAM FOGG PUBLIC LIBRARY",
      "system": "WILLIAM FOGG PUBLIC LIBRARY",
      "address": "116 OLD ROAD, ELIOT, ME",
      "website": "https://www.williamfogglibrary.org/",
      "formUrl": null,
      "formStatus": "unknown",
      "zipcodes": [
        "03903",
        "03905"
      ],
      "id": "william-fogg-public-library-me"
    },
    {
      "name": "RICE PUBLIC LIBRARY",
      "system": "RICE PUBLIC LIBRARY",
      "address": "8 WENTWORTH STREET, KITTERY, ME",
      "website": "https://rice.lib.me.us/",
      "formUrl": null,
      "formStatus": "unknown",
      "zipcodes": [
        "03904",
        "03905"
      ],
      "id": "rice-public-library-me"
    },
    {
      "name": "D.A. HURD LIBRARY",
      "system": "D.A. HURD LIBRARY",
      "address": "41 HIGH STREET, NORTH BERWICK, ME",
      "website": "https://dahurdlibrary.org/",
      "formUrl": null,
      "formStatus": "unknown",
      "zipcodes": [
        "03906"
      ],
      "id": "da-hurd-library-me"
    },
    {
      "name": "SOUTH BERWICK PUBLIC LIBRARY",
      "system": "SOUTH BERWICK PUBLIC LIBRARY",
      "address": "27 YOUNG STREET, SOUTH BERWICK, ME",
      "website": "https://southberwickmaine.org/library/",
      "formUrl": null,
      "formStatus": "unknown",
      "zipcodes": [
        "03908"
      ],
      "id": "south-berwick-public-library-me"
    },
    {
      "name": "YORK PUBLIC LIBRARY",
      "system": "YORK PUBLIC LIBRARY",
      "address": "15 LONG SANDS ROAD, YORK, ME",
      "website": "https://yorkpubliclibrary.org/",
      "formUrl": null,
      "formStatus": "unknown",
      "zipcodes": [
        "03902",
        "03905",
        "03909"
      ],
      "id": "york-public-library-me"
    },
    {
      "name": "BERWICK PUBLIC LIBRARY",
      "system": "BERWICK PUBLIC LIBRARY",
      "address": "103 OLD PINE HILL ROAD NORTH, BERWICK, ME",
      "website": "https://www.berwick.lib.me.us/",
      "formUrl": null,
      "formStatus": "unknown",
      "zipcodes": [
        "03901"
      ],
      "id": "berwick-public-library-me"
    },
    {
      "name": "OGUNQUIT MEMORIAL LIBRARY",
      "system": "OGUNQUIT MEMORIAL LIBRARY",
      "address": "166 SHORE ROAD, OGUNQUIT, ME",
      "website": "https://ogunquitlibrary.com/",
      "formUrl": null,
      "formStatus": "unknown",
      "zipcodes": [
        "03902",
        "03907"
      ],
      "id": "ogunquit-memorial-library-me"
    }
  ]
}