{
  "libraries": [
    {
      "name": "FLORENCE PUBLIC LIBRARY",
      "system": "FLORENCE PUBLIC LIBRARY",
      "address": "324 MAIN ST., FLORENCE, KS",
      "website": "https://florenceks.com/text/city/city_library.htm",
      "formUrl": null,
      "formStatus": "unknown",
      "zipcodes": [
        "66851",
        "76527",
        "76530",
        "76574",
        "76578",
        "78615",
        "78626",
        "78628",
        "78681",
        "78717",
        "78729"
      ]
    },
    {
      "name": "GOESSEL PUBLIC LIBRARY",
      "system": "GOESSEL PUBLIC LIBRARY",
      "address": "101 S. CEDAR, GOESSEL, KS",
      "website": "https://librarytechnology.org/library/18204",
      "formUrl": null,
      "formStatus": "unknown",
      "zipcodes": [
        "66858",
        "66859",
        "67053",
        "67063",
        "67073",
        "67438",
        "67475",
        "67483"
      ]
    },
    {
      "name": "LEON PUBLIC LIBRARY",
      "system": "LEON PUBLIC LIBRARY",
      "address": "200 W 1ST ST, LEON, IA",
      "website": "https://cityofleon.org/library-2",
      "formUrl": null,
      "formStatus": "unknown",
      "zipcodes": [
        "50144",
        "66842",
        "67002",
        "67012",
        "67017",
        "67041",
        "67072",
        "67074",
        "670HH",
        "67132",
        "67144"
      ]
    },
    {
      "name": "DOUGLASS PUBLIC LIBRARY",
      "system": "DOUGLASS PUBLIC LIBRARY",
      "address": "319 S. FOREST, DOUGLASS, KS",
      "website": "https://douglass.scklslibrary.info/",
      "formUrl": null,
      "formStatus": "unknown",
      "zipcodes": [
        "66842",
        "67002",
        "67012",
        "67017",
        "67039",
        "67041",
        "67072",
        "67074",
        "670HH",
        "67132",
        "67144"
      ]
    },
    {
      "name": "AUGUSTA PUBLIC LIBRARY",
      "system": "AUGUSTA PUBLIC LIBRARY",
      "address": "1609 STATE ST., AUGUSTA, KS",
      "website": "https://www.augustapubliclibrary.com/",
      "formUrl": null,
      "formStatus": "unknown",
      "zipcodes": [
        "66842",
        "67002",
        "67010",
        "67012",
        "67017",
        "67041",
        "67072",
        "67074",
        "670HH",
        "67132",
        "67144"
      ]
    },
    {
      "name": "BRADFORD MEMORIAL LIBRARY",
      "system": "BRADFORD MEMORIAL LIBRARY",
      "address": "611 S. WASHINGTON, EL DORADO, KS",
      "website": "https://bradford.scklslibrary.info/",
      "formUrl": null,
      "formStatus": "unknown",
      "zipcodes": [
        "66842",
        "67002",
        "67012",
        "67017",
        "67041",
        "67042",
        "67072",
        "67074",
        "670HH",
        "67132",
        "67144"
      ]
    },
    {
      "name": "EUREKA PUBLIC LIBRARY",
      "system": "EUREKA PUBLIC LIBRARY",
      "address": "606 NORTH MAIN, EUREKA, KS",
      "website": "http://eurekapubliclibrary.org/",
      "formUrl": null,
      "formStatus": "unknown",
      "zipcodes": [
        "66860",
        "66863",
        "66870",
        "67045",
        "67122",
        "67137"
      ]
    },
    {
      "name": "POTWIN PUBLIC LIBRARY",
      "system": "POTWIN PUBLIC LIBRARY",
      "address": "126 N. RANDALL, POTWIN, KS",
      "website": "https://potwinks.com/library/",
      "formUrl": null,
      "formStatus": "unknown",
      "zipcodes": [
        "66842",
        "67002",
        "67012",
        "67017",
        "67041",
        "67072",
        "67074",
        "670HH",
        "67123",
        "67132",
        "67144"
      ]
    },
    {
      "name": "WHITEWATER MEMORIAL LIBRARY",
      "system": "WHITEWATER MEMORIAL LIBRARY",
      "address": "118 EAST TOPEKA, WHITEWATER, KS",
      "website": "https://whitewaterks.gov/whitewater-memorial-library",
      "formUrl": null,
      "formStatus": "unknown",
      "zipcodes": [
        "66842",
        "67002",
        "67012",
        "67017",
        "67041",
        "67072",
        "67074",
        "670HH",
        "67132",
        "67144",
        "67154"
      ]
    },
    {
      "name": "ROSE HILL PUBLIC LIBRARY",
      "system": "ROSE HILL PUBLIC LIBRARY",
      "address": "306 N ROSE HILL RD, ROSE HILL, KS",
      "website": "https://rosehill.scklslibrary.info/",
      "formUrl": null,
      "formStatus": "unknown",
      "zipcodes": [
        "66842",
        "67002",
        "67012",
        "67017",
        "67041",
        "67072",
        "67074",
        "670HH",
        "67132",
        "67133",
        "67144"
      ]
    },
    {
      "name": "BURNS PUBLIC LIBRARY",
      "system": "BURNS PUBLIC LIBRARY",
      "address": "104 NORTH WASHINGTON AVE, BURNS, KS",
      "website": "https://www.chamberofcommerce.com/united-states/kansas/burns/public-library/2000902030-burns-public-library",
      "formUrl": null,
      "formStatus": "unknown",
      "zipcodes": [
        "66840",
        "66858",
        "66859",
        "67063",
        "67073",
        "67438",
        "67475",
        "67483"
      ]
    },
    {
      "name": "DWIGHT PUBLIC LIBRARY",
      "system": "DWIGHT PUBLIC LIBRARY",
      "address": "616 MAIN STREET, DWIGHT, KS",
      "website": "http://dwightks.net/library",
      "formUrl": null,
      "formStatus": "unknown",
      "zipcodes": [
        "66838",
        "66849"
      ]
    },
    {
      "name": "ELM CREEK TOWNSHIP LIBRARY",
      "system": "ELM CREEK TOWNSHIP LIBRARY",
      "address": "213 NORTH 5TH ST., WILSEY, KS",
      "website": "https://librarytechnology.org/library/18201",
      "formUrl": null,
      "formStatus": "unknown",
      "zipcodes": [
        "66838",
        "66873"
      ]
    },
    {
      "name": "WHITE CITY PUBLIC LIBRARY",
      "system": "WHITE CITY PUBLIC LIBRARY",
      "address": "111 E MACKENZIE, WHITE CITY, KS",
      "website": "https://www.chamberofcommerce.com/business-directory/kansas/white-city/public-library/2029213213-white-city-public-library",
      "formUrl": null,
      "formStatus": "unknown",
      "zipcodes": [
        "66838",
        "66872"
      ]
    },
    {
      "name": "BURNLEY MEMORIAL/FALLS TOWNSHIP",
      "system": "BURNLEY MEMORIAL/FALLS TOWNSHIP",
      "address": "405 N. OAK, COTTONWOOD FALLS, KS",
      "website": "https://www.findglocal.com/US/Cottonwood-Falls/263182893005/Burnley-Memorial-Library",
      "formUrl": null,
      "formStatus": "unknown",
      "zipcodes": [
        "66843",
        "66845",
        "66850",
        "66862",
        "66869",
        "668HH"
      ]
    },
    {
      "name": "HARTFORD/ELMENDARO TOWNSHIP",
      "system": "HARTFORD/ELMENDARO TOWNSHIP",
      "address": "224 COMMERCIAL ST., HARTFORD, KS",
      "website": "https://librarytechnology.org/library/18220",
      "formUrl": null,
      "formStatus": "unknown",
      "zipcodes": [
        "66830",
        "66854",
        "66864",
        "66865",
        "66868"
      ]
    },
    {
      "name": "AMERICUS TOWNSHIP LIBRARY",
      "system": "AMERICUS TOWNSHIP LIBRARY",
      "address": "710 MAIN ST., AMERICUS, KS",
      "website": "https://cityofamericus.municipalimpact.com/library",
      "formUrl": null,
      "formStatus": "unknown",
      "zipcodes": [
        "66830",
        "66835",
        "66864",
        "66865",
        "66868"
      ]
    },
    {
      "name": "PEABODY TOWNSHIP LIBRARY",
      "system": "PEABODY TOWNSHIP LIBRARY",
      "address": "214 N. WALNUT, PEABODY, KS",
      "website": "http://peabody.mykansaslibrary.org/",
      "formUrl": null,
      "formStatus": "unknown",
      "zipcodes": [
        "66858",
        "66859",
        "66866",
        "67063",
        "67073",
        "67438",
        "67475",
        "67483"
      ]
    },
    {
      "name": "MARION CITY LIBRARY",
      "system": "MARION CITY LIBRARY",
      "address": "101 LIBRARY ST, MARION, KS",
      "website": "https://www.marionks.net/1292/Library",
      "formUrl": null,
      "formStatus": "unknown",
      "zipcodes": [
        "66858",
        "66859",
        "66861",
        "67063",
        "67073",
        "67438",
        "67475",
        "67483"
      ]
    },
    {
      "name": "COUNCIL GROVE PUBLIC LIBRARY",
      "system": "COUNCIL GROVE PUBLIC LIBRARY",
      "address": "829 W. MAIN ST., COUNCIL GROVE, KS",
      "website": "https://www.councilgrove.com/business-directory/council-grove-public-library",
      "formUrl": null,
      "formStatus": "unknown",
      "zipcodes": [
        "66838",
        "66846"
      ]
    },
    {
      "name": "EMPORIA PUBLIC LIBRARY",
      "system": "EMPORIA PUBLIC LIBRARY",
      "address": "110 E. SIXTH AVENUE, EMPORIA, KS",
      "website": "https://www.emporialibrary.org/",
      "formUrl": null,
      "formStatus": "unknown",
      "zipcodes": [
        "66801",
        "66830",
        "66864",
        "66865",
        "66868"
      ]
    },
    {
      "name": "LYON COUNTY LIBRARY DIST. #1",
      "system": "LYON COUNTY LIBRARY DIST. #1",
      "address": "421 MAIN, ALLEN, KS",
      "website": "https://librarytechnology.org/library/18215",
      "formUrl": null,
      "formStatus": "unknown",
      "zipcodes": [
        "66830",
        "66833",
        "66864",
        "66865",
        "66868"
      ]
    },
    {
      "name": "HAMILTON CITY LIBRARY",
      "system": "HAMILTON CITY LIBRARY",
      "address": "21 E. MAIN, HAMILTON, KS",
      "website": "https://hamiltoncitylibrary.org/",
      "formUrl": null,
      "formStatus": "unknown",
      "zipcodes": [
        "66853",
        "66860",
        "66863",
        "66870",
        "67122",
        "67137"
      ]
    },
    {
      "name": "COFFEY COUNTY LIBRARY",
      "system": "COFFEY COUNTY LIBRARY",
      "address": "410 JUNIATTA STREET, BURLINGTON, KS",
      "website": "https://cclibks.org/burlington/",
      "formUrl": null,
      "formStatus": "unknown",
      "zipcodes": [
        "66839",
        "66852",
        "66856",
        "66857",
        "66871"
      ]
    }
  ]
}