{
  "libraries": [
    {
      "name": "ASSUMPTION PARISH LIBRARY",
      "system": "ASSUMPTION PARISH LIBRARY",
      "address": "293 NAPOLEON AVENUE, NAPOLEONVILLE, LA",
      "website": "https://assumptionlibrary.com/napoleonville/",
      "formUrl": null,
      "formStatus": "unknown",
      "zipcodes": [
        "70390"
      ]
    },
    {
      "name": "ASCENSION PARISH LIBRARY",
      "system": "ASCENSION PARISH LIBRARY",
      "address": "500 MISSISSIPPI STREET, DONALDSONVILLE, LA",
      "website": "http://www.myapl.org",
      "formUrl": null,
      "formStatus": "unknown",
      "zipcodes": [
        "70346"
      ]
    },
    {
      "name": "LAFOURCHE PARISH PUBLIC LIBRARY",
      "system": "LAFOURCHE PARISH PUBLIC LIBRARY",
      "address": "705 WEST 5TH STREET, THIBODAUX, LA",
      "website": "https://www.lafourche.org/",
      "formUrl": null,
      "formStatus": "unknown",
      "zipcodes": [
        "70301"
      ]
    },
    {
      "name": "TERREBONNE PARISH LIBRARY",
      "system": "TERREBONNE PARISH LIBRARY",
      "address": "151 LIBRARY DRIVE, HOUMA, LA",
      "website": "https://mytpl.org/",
      "formUrl": null,
      "formStatus": "unknown",
      "zipcodes": [
        "70360"
      ]
    },
    {
      "name": "MORGAN CITY PUBLIC LIBRARY",
      "system": "MORGAN CITY PUBLIC LIBRARY",
      "address": "220 EVERETT STREET, MORGAN CITY, LA",
      "website": "http://morgancitylibrary.com/",
      "formUrl": null,
      "formStatus": "unknown",
      "zipcodes": [
        "70380"
      ]
    }
  ]
}